wait_for2/__init__.py
wait_for2/impl.py
wait_for2-0.2.0.dist-info/LICENSE
wait_for2-0.2.0.dist-info/METADATA
wait_for2-0.2.0.dist-info/NOTICE
wait_for2-0.2.0.dist-info/WHEEL
wait_for2-0.2.0.dist-info/top_level.txt
wait_for2-0.2.0.dist-info/RECORD
